Metadata-Version: 2.1
Name: shoesexe
Version: 0.0.1
Summary: Running shoes.
Home-page: UNKNOWN
Author: Kfir Nissim
License: MIT
Platform: UNKNOWN
